argostranslatefiles/__init__.py
argostranslatefiles/abstract_file.py
argostranslatefiles/argostranslatefiles.py
argostranslatefiles/formats/__init__.py
argostranslatefiles/formats/abstract_xml.py
argostranslatefiles/formats/epub.py
argostranslatefiles/formats/html.py
argostranslatefiles/formats/pdf.py
argostranslatefiles/formats/srt.py
argostranslatefiles/formats/txt.py
argostranslatefiles/formats/opendocument/__init__.py
argostranslatefiles/formats/opendocument/odp.py
argostranslatefiles/formats/opendocument/odt.py
argostranslatefiles/formats/openxml/__init__.py
argostranslatefiles/formats/openxml/docx.py
argostranslatefiles/formats/openxml/pptx.py
tests/__init__.py
tests/test_init.py
argos_translate_files-1.4.1.dist-info/LICENSE
argos_translate_files-1.4.1.dist-info/METADATA
argos_translate_files-1.4.1.dist-info/WHEEL
argos_translate_files-1.4.1.dist-info/top_level.txt
argos_translate_files-1.4.1.dist-info/RECORD
