Metadata-Version: 2.1
Name: argos-translate-files
Version: 1.4.1
Summary: Translate files with Argos Translate
Home-page: https://github.com/LibreTranslate/argos-translate-files
Author: S. Thuret
Author-email: contact@sebastien-thuret.fr
License: UNKNOWN
Platform: UNKNOWN
Requires-Dist: beautifulsoup4>=4.9.3
Requires-Dist: lxml>=4.9.2
Requires-Dist: argostranslate>=1.5.1
Requires-Dist: translatehtml>=1.5.1
Requires-Dist: pysrt>=1.1.2
Requires-Dist: PyMuPDF>=1.24.11
